withmake/__init__.py
withmake/script.py
withmake-0.1.0.dist-info/METADATA
withmake-0.1.0.dist-info/WHEEL
withmake-0.1.0.dist-info/top_level.txt
withmake-0.1.0.dist-info/RECORD
