Metadata-Version: 2.1
Name: withmake
Version: 0.1.0
Summary: Python Client for the Make.com API
Home-page: https://github.com/Akiren/withMake
Author: Lorenzo Lee
Author-email: zo@lotic.digital
License: MIT
Platform: UNKNOWN
Classifier: Intended Audience :: Developers
Classifier: License :: OSI Approved :: MIT License
Classifier: Programming Language :: Python
Classifier: Programming Language :: Python :: 3
Classifier: Programming Language :: Python :: 3.6
Classifier: Programming Language :: Python :: 3.7
Classifier: Programming Language :: Python :: 3.8
Classifier: Programming Language :: Python :: 3.9
Classifier: Operating System :: OS Independent
Requires-Dist: requests
